goap/Action.py
goap/Automaton.py
goap/Errors.py
goap/Planner.py
goap/Sensor.py
goap/WorldState.py
goap/__init__.py
goap/utils/__init__.py
goap/utils/aws/__init__.py
goap/utils/command/__init__.py
goap/utils/commons/__init__.py
goap/utils/gcp/__init__.py
goap/utils/os/TODO.md
goap/utils/os/__init__.py
goap/utils/os/shell_command.py
goap-0.3.0.dist-info/LICENSE
goap-0.3.0.dist-info/WHEEL
goap-0.3.0.dist-info/METADATA
goap-0.3.0.dist-info/RECORD
